{
  "pageContext": {
    "jsonName": "2013-1-13-riak-core-myappping-1ec",
    "internalComponentName": "Component2013113RiakCoreMyappping",
    "path": "/2013/1/13/riak-core-myappping/",
    "component":
      "/Users/biscarch/github/christopherbiscardi/christopherbiscardi.github.com/src/blog-post.js",
    "componentChunkName": "component---src-blog-post-js",
    "context": {},
    "updatedAt": 1531007356406,
    "pluginCreator___NODE": "Plugin default-site-plugin",
    "pluginCreatorId": "Plugin default-site-plugin",
    "componentPath":
      "/Users/biscarch/github/christopherbiscardi/christopherbiscardi.github.com/src/blog-post.js"
  }
}
